tornadopy/__init__.py
tornadopy/correlation.py
tornadopy/distribution.py
tornadopy/plot.py
tornadopy/processor.py
tornadopy-0.1.54.dist-info/licenses/LICENSE
tornadopy-0.1.54.dist-info/METADATA
tornadopy-0.1.54.dist-info/WHEEL
tornadopy-0.1.54.dist-info/top_level.txt
tornadopy-0.1.54.dist-info/RECORD
