Metadata-Version: 2.4
Name: tornadopy
Version: 0.1.54
Summary: A Python library for tornado chart generation and analysis
Home-page: https://github.com/kkollsga/tornadopy
Author: Kristian dF Kollsgård
Author-email: Kristian dF Kollsgård <kkollsg@gmail.com>
License: MIT
Project-URL: Homepage, https://github.com/kkollsga/tornadopy
Project-URL: Documentation, https://github.com/kkollsga/tornadopy#readme
Project-URL: Repository, https://github.com/kkollsga/tornadopy
Project-URL: Issues, https://github.com/kkollsga/tornadopy/issues
Keywords: tornado,chart,visualization,uncertainty,analysis
Classifier: Development Status :: 3 - Alpha
Classifier: Intended Audience :: Science/Research
Classifier: Topic :: Scientific/Engineering :: Visualization
Classifier: License :: OSI Approved :: MIT License
Classifier: Programming Language :: Python :: 3
Classifier: Programming Language :: Python :: 3.9
Classifier: Programming Language :: Python :: 3.10
Classifier: Programming Language :: Python :: 3.11
Classifier: Programming Language :: Python :: 3.12
Classifier: Programming Language :: Python :: 3.13
Requires-Python: >=3.9
License-File: LICENSE
Requires-Dist: numpy>=1.20.0
Requires-Dist: polars>=0.18.0
Requires-Dist: fastexcel>=0.9.0
Requires-Dist: matplotlib>=3.5.0
Provides-Extra: dev
Requires-Dist: pytest>=7.0.0; extra == "dev"
Requires-Dist: black>=22.0.0; extra == "dev"
Requires-Dist: flake8>=4.0.0; extra == "dev"
Dynamic: author
Dynamic: home-page
Dynamic: license-file
Dynamic: requires-python
